fmf_jinja/__init__.py
fmf_jinja/__main__.py
fmf_jinja/_version.py
fmf_jinja/generators.py
fmf_jinja/py.typed
fmf_jinja/template.py
fmf_jinja/utils.py
fmf_jinja/_compat/__init__.py
fmf_jinja/cli/__init__.py
fmf_jinja/cli/main.py
fmf_jinja/schema/copy.yaml
fmf_jinja/schema/link.yaml
fmf_jinja/schema/main.yaml
fmf_jinja/schema/template.yaml
fmf_jinja-0.1.0.dist-info/METADATA
fmf_jinja-0.1.0.dist-info/WHEEL
fmf_jinja-0.1.0.dist-info/entry_points.txt
fmf_jinja-0.1.0.dist-info/licenses/LICENSE.md
fmf_jinja-0.1.0.dist-info/RECORD
