Metadata-Version: 2.3
Name: fmf-jinja
Version: 0.1.0
Summary: Jinja-style templater using fmf metadata
Project-URL: Homepage, https://github.com/LecrisUT/fmf-jinja
Author-email: Cristian Le <git@lecris.dev>
Maintainer-email: Cristian Le <git@lecris.dev>
License: GPL-3.0-or-later
Keywords: metadata,template
Classifier: Development Status :: 3 - Alpha
Classifier: Programming Language :: Python :: 3.9
Classifier: Programming Language :: Python :: 3.10
Classifier: Programming Language :: Python :: 3.11
Classifier: Programming Language :: Python :: 3.12
Classifier: Programming Language :: Python :: 3.13
Classifier: Topic :: Utilities
Requires-Python: >=3.9
Requires-Dist: attrs>=23.2.0
Requires-Dist: click
Requires-Dist: fmf
Requires-Dist: jinja2
Provides-Extra: docs
Requires-Dist: furo; extra == 'docs'
Requires-Dist: myst-parser; extra == 'docs'
Requires-Dist: sphinx; extra == 'docs'
Requires-Dist: sphinx-autodoc-typehints; extra == 'docs'
Requires-Dist: sphinx-click; extra == 'docs'
Requires-Dist: sphinx-tippy; extra == 'docs'
Provides-Extra: test
Requires-Dist: pytest; extra == 'test'
Provides-Extra: test-cov
Requires-Dist: pytest; extra == 'test-cov'
Requires-Dist: pytest-cov; extra == 'test-cov'
